kgb/__init__.py
kgb/agency.py
kgb/asserts.py
kgb/calls.py
kgb/contextmanagers.py
kgb/errors.py
kgb/ops.py
kgb/pycompat.py
kgb/pytest_plugin.py
kgb/signature.py
kgb/spies.py
kgb/utils.py
kgb/tests/__init__.py
kgb/tests/base.py
kgb/tests/test_context_managers.py
kgb/tests/test_function_spy.py
kgb/tests/test_ops.py
kgb/tests/test_pytest_plugin.py
kgb/tests/test_spy_agency.py
kgb/tests/test_spy_call.py
kgb/tests/py3/__init__.py
kgb/tests/py3/test_function_spy.py
kgb-7.1.1.dist-info/AUTHORS
kgb-7.1.1.dist-info/LICENSE
kgb-7.1.1.dist-info/METADATA
kgb-7.1.1.dist-info/WHEEL
kgb-7.1.1.dist-info/entry_points.txt
kgb-7.1.1.dist-info/top_level.txt
kgb-7.1.1.dist-info/RECORD
